{
    "task": "Which of the following equations is equivalent to $7(x - 5) = 0$?",
    "answers": {
        "A": "$x - 2 = -5$",
        "B": "$x = 3$",
        "C": "$x - 7 = 5$",
        "D": "$x = 5$"
    },
    "correct": {
        "A": false,
        "B": false,
        "C": false,
        "D": true
    },
    "difficulty": "Easy",
    "explanation": "Choice D is correct.\nDividing each side of the given equation by 7 yields $x - 5 = 0$.\nTherefore, the equation $x = 5$ is equivalent to the given equation.",
    "id": "98c3b124",
    "subcategory": "Linear_equations_in_one_variable"
}