{
    "task": "Solve the system of equations for $(x, y)$:\n$$ 8x -10y = 4\n $$$$ -1x -4y = 4\n $$",
    "answers": {
        "A": "$(-\\frac{4}{7}, -\\frac{5}{14})$",
        "B": "$(-\\frac{1}{14}, -\\frac{6}{7})$",
        "C": "$(-\\frac{6}{7}, -\\frac{4}{7})$",
        "D": "$(-\\frac{4}{7}, -\\frac{6}{7})$"
    },
    "correct": {
        "A": false,
        "B": false,
        "C": false,
        "D": true
    },
    "explanation": "We solve the system using elimination or substitution. The determinant is computed as 8 * -4 - (-10) * -1 = -42, which is nonzero, so a unique solution exists. Solving for $x$ and $y$, we find $(x, y) = (-4/7, -6/7)$.",
    "difficulty": "Medium",
    "id": "a292f9fb",
    "subcategory": "Systems_of_two_linear_equations_in_two_variables"
}